{
	"id": "7a113a39-138a-3eda-00e1-3e6fd4eed82f",
	"name": "建材展示线上",
	"description": "",
	"order": [],
	"folders": [
		{
			"owner": "1540173",
			"lastUpdatedBy": "1540173",
			"lastRevision": 1637690250,
			"folder": null,
			"id": "d236000b-164d-c95c-5f73-7af83843bae7",
			"name": "会员类",
			"description": "",
			"order": [
				"703793b0-2f0c-9516-3c14-1be6b37c4872",
				"0138a83e-7dbe-1c9e-0310-463b13cedb2d",
				"bb9aba83-d84d-aeb6-fc5c-b71e30e8f423",
				"1a84267c-b9c4-3fd1-eebd-24da548ecd89",
				"0aee69c3-f28b-e1ad-ed20-43fe9f9ce03e",
				"bf7fc7ec-162d-e6fe-50c9-fb4781e33b39",
				"830f36a8-db8c-0f0b-610f-6fcdf33377ec",
				"73bc69f5-b918-444d-9d98-e9f0a38c5106",
				"12ee18c9-8273-ae77-894b-74e82fa1bd7f",
				"5be820de-65c8-33c6-e2a2-1797d89b4492"
			]
		},
		{
			"owner": "1540173",
			"lastUpdatedBy": "1540173",
			"lastRevision": 1639264397,
			"folder": null,
			"id": "cd2f7897-8761-313f-4758-d65229a2417d",
			"name": "关注类",
			"description": "",
			"order": [
				"2c3d04c1-89bd-74d3-01f8-13a10656ca81",
				"597a4642-25df-f562-3e74-0bec166ad291",
				"d1615470-1d86-4ed9-1ee8-ca8b7dd89ed0"
			],
			"collectionId": "a4d56784-5fdb-2950-e30f-747d3b87ac0a"
		},
		{
			"owner": "1540173",
			"lastUpdatedBy": "1540173",
			"lastRevision": 1639264397,
			"folder": null,
			"id": "4307cc78-0c0e-d4a1-0a9e-2a0fa9ae9a6b",
			"name": "收藏类",
			"description": "",
			"order": [
				"f764ab22-bdb0-38a2-891c-d06a945cc822",
				"b9b18491-5b3e-c5b8-51b3-3fa6892eb8eb",
				"3789c281-b628-304b-3186-d2e6d0b61650"
			],
			"collectionId": "a4d56784-5fdb-2950-e30f-747d3b87ac0a"
		},
		{
			"owner": "1540173",
			"lastUpdatedBy": "1540173",
			"lastRevision": 1639103148,
			"folder": null,
			"id": "f5318e9b-3886-a1a7-5285-e1ee93af19d3",
			"name": "显示类",
			"description": "",
			"order": [
				"beb2e471-954e-9e41-5040-d714fd031150",
				"dfc53445-7ca8-2640-cef8-07417a1d6299",
				"72aebc71-c50c-951d-06db-209404e00736",
				"2dcf88f8-1a87-aa89-ca84-28e7261b8a82",
				"939d3449-fd9d-8d96-cd0c-6129a5592e06"
			]
		}
	],
	"timestamp": 1497923130342,
	"owner": "1540173",
	"public": false,
	"requests": [
		{
			"id": "0138a83e-7dbe-1c9e-0310-463b13cedb2d",
			"headers": "",
			"headerData": [],
			"url": "http://jiancai.cq1b1.com/api.php/Register",
			"queryParams": [],
			"preRequestScript": "",
			"pathVariables": {},
			"pathVariableData": [],
			"method": "POST",
			"data": [
				{
					"key": "version",
					"value": "1.1",
					"type": "text",
					"enabled": true
				},
				{
					"key": "apikey",
					"value": "f74dd39951a0b6bbed0fe73606ea5476",
					"type": "text",
					"enabled": true
				},
				{
					"key": "phone",
					"value": "15696154320",
					"type": "text",
					"enabled": true
				},
				{
					"key": "pass",
					"value": "123456",
					"type": "text",
					"enabled": true
				}
			],
			"dataMode": "params",
			"tests": "",
			"currentHelper": "normal",
			"helperAttributes": {},
			"time": 1497924388595,
			"name": "注册",
			"description": "",
			"collectionId": "7a113a39-138a-3eda-00e1-3e6fd4eed82f"
		},
		{
			"id": "0aee69c3-f28b-e1ad-ed20-43fe9f9ce03e",
			"headers": "",
			"headerData": [],
			"url": "http://jiancai.cq1b1.com/api.php/Register/pwd_wjedit",
			"queryParams": [],
			"preRequestScript": "",
			"pathVariables": {},
			"pathVariableData": [],
			"method": "POST",
			"data": [
				{
					"key": "version",
					"value": "1.1",
					"type": "text",
					"enabled": true
				},
				{
					"key": "apikey",
					"value": "f74dd39951a0b6bbed0fe73606ea5476",
					"type": "text",
					"enabled": true
				},
				{
					"key": "phone",
					"value": "15696154320",
					"type": "text",
					"enabled": true
				},
				{
					"key": "pass",
					"value": "123456",
					"type": "text",
					"enabled": true
				}
			],
			"dataMode": "params",
			"tests": "",
			"currentHelper": "normal",
			"helperAttributes": {},
			"time": 1497924987872,
			"name": "找回密码",
			"description": "",
			"collectionId": "7a113a39-138a-3eda-00e1-3e6fd4eed82f"
		},
		{
			"id": "12ee18c9-8273-ae77-894b-74e82fa1bd7f",
			"headers": "",
			"headerData": [],
			"url": "http://jiancai.cq1b1.com/api.php/User/kaidian",
			"queryParams": [],
			"preRequestScript": "",
			"pathVariables": {},
			"pathVariableData": [],
			"method": "POST",
			"data": [
				{
					"key": "version",
					"value": "1.1",
					"type": "text",
					"enabled": true
				},
				{
					"key": "apikey",
					"value": "f74dd39951a0b6bbed0fe73606ea5476",
					"type": "text",
					"enabled": true
				},
				{
					"key": "user_id",
					"value": "1",
					"type": "text",
					"enabled": true
				},
				{
					"key": "bus_title",
					"value": "店铺名称",
					"description": "",
					"type": "text",
					"enabled": true
				},
				{
					"key": "bus_username",
					"value": "店主姓名",
					"description": "",
					"type": "text",
					"enabled": true
				},
				{
					"key": "bus_phone",
					"value": "15600000000",
					"description": "",
					"type": "text",
					"enabled": true
				},
				{
					"key": "bus_type",
					"value": "1:2:3",
					"description": "",
					"type": "text",
					"enabled": true
				},
				{
					"key": "bus_logo",
					"value": "",
					"description": "",
					"type": "file",
					"enabled": true
				}
			],
			"dataMode": "params",
			"tests": "",
			"currentHelper": "normal",
			"helperAttributes": {},
			"time": 1498124210825,
			"name": "申请开店",
			"description": "",
			"collectionId": "7a113a39-138a-3eda-00e1-3e6fd4eed82f"
		},
		{
			"id": "1a84267c-b9c4-3fd1-eebd-24da548ecd89",
			"headers": "",
			"headerData": [],
			"url": "http://jiancai.cq1b1.com/api.php/Register/gain_yzm",
			"queryParams": [],
			"preRequestScript": "",
			"pathVariables": {},
			"pathVariableData": [],
			"method": "POST",
			"data": [
				{
					"key": "version",
					"value": "1.1",
					"type": "text",
					"enabled": true
				},
				{
					"key": "apikey",
					"value": "f74dd39951a0b6bbed0fe73606ea5476",
					"type": "text",
					"enabled": true
				},
				{
					"key": "phone",
					"value": "15696154320",
					"type": "text",
					"enabled": true
				}
			],
			"dataMode": "params",
			"tests": "",
			"currentHelper": "normal",
			"helperAttributes": {},
			"time": 1497925040627,
			"name": "找回密码获取验证码",
			"description": "",
			"collectionId": "7a113a39-138a-3eda-00e1-3e6fd4eed82f"
		},
		{
			"id": "2c3d04c1-89bd-74d3-01f8-13a10656ca81",
			"headers": "",
			"headerData": [],
			"url": "http://jiancai.cq1b1.com/api.php/Public/guanzhu_add",
			"queryParams": [],
			"preRequestScript": "",
			"pathVariables": {},
			"pathVariableData": [],
			"method": "POST",
			"data": [
				{
					"key": "version",
					"value": "1.1",
					"type": "text",
					"enabled": true
				},
				{
					"key": "apikey",
					"value": "f74dd39951a0b6bbed0fe73606ea5476",
					"type": "text",
					"enabled": true
				},
				{
					"key": "user_id",
					"value": "1",
					"type": "text",
					"enabled": true
				},
				{
					"key": "bus_id",
					"value": "1",
					"type": "text",
					"enabled": true
				}
			],
			"dataMode": "params",
			"tests": "",
			"currentHelper": "normal",
			"helperAttributes": {},
			"time": 1498125273045,
			"name": "添加关注",
			"description": "user_id：用户id；\nbus_id：商家id",
			"collectionId": "7a113a39-138a-3eda-00e1-3e6fd4eed82f"
		},
		{
			"id": "2dcf88f8-1a87-aa89-ca84-28e7261b8a82",
			"headers": "",
			"headerData": [],
			"url": "http://jiancai.cq1b1.com/api.php/Public/bus_list",
			"queryParams": [],
			"preRequestScript": "",
			"pathVariables": {},
			"pathVariableData": [],
			"method": "POST",
			"data": [
				{
					"key": "version",
					"value": "1.1",
					"type": "text",
					"enabled": true
				},
				{
					"key": "apikey",
					"value": "f74dd39951a0b6bbed0fe73606ea5476",
					"type": "text",
					"enabled": true
				},
				{
					"key": "type_id",
					"value": "1",
					"type": "text",
					"enabled": true
				},
				{
					"key": "page",
					"value": "1",
					"description": "",
					"type": "text",
					"enabled": true
				},
				{
					"key": "zuixin",
					"value": "1",
					"description": "",
					"type": "text",
					"enabled": true
				}
			],
			"dataMode": "params",
			"tests": "",
			"currentHelper": "normal",
			"helperAttributes": {},
			"time": 1498124086982,
			"name": "店铺列表",
			"description": "type_id：分类id；\npage：页码；\nzuixin：0时间升序，1倒序",
			"collectionId": "7a113a39-138a-3eda-00e1-3e6fd4eed82f"
		},
		{
			"id": "3789c281-b628-304b-3186-d2e6d0b61650",
			"headers": "",
			"headerData": [],
			"url": "http://jiancai.cq1b1.com/api.php/Public/shoucang_del",
			"queryParams": [],
			"preRequestScript": "",
			"pathVariables": {},
			"pathVariableData": [],
			"method": "POST",
			"data": [
				{
					"key": "version",
					"value": "1.1",
					"type": "text",
					"enabled": true
				},
				{
					"key": "apikey",
					"value": "f74dd39951a0b6bbed0fe73606ea5476",
					"type": "text",
					"enabled": true
				},
				{
					"key": "user_id",
					"value": "1",
					"type": "text",
					"enabled": true
				},
				{
					"key": "goods_id",
					"value": "1",
					"description": "",
					"type": "text",
					"enabled": true
				}
			],
			"dataMode": "params",
			"tests": "",
			"currentHelper": "normal",
			"helperAttributes": {},
			"time": 1498178760905,
			"name": "删除收藏",
			"description": "id：收藏id",
			"collectionId": "7a113a39-138a-3eda-00e1-3e6fd4eed82f"
		},
		{
			"id": "597a4642-25df-f562-3e74-0bec166ad291",
			"headers": "",
			"headerData": [],
			"url": "http://jiancai.cq1b1.com/api.php/Public/guanzhu_list",
			"queryParams": [],
			"preRequestScript": "",
			"pathVariables": {},
			"pathVariableData": [],
			"method": "POST",
			"data": [
				{
					"key": "version",
					"value": "1.1",
					"type": "text",
					"enabled": true
				},
				{
					"key": "apikey",
					"value": "f74dd39951a0b6bbed0fe73606ea5476",
					"type": "text",
					"enabled": true
				},
				{
					"key": "user_id",
					"value": "1",
					"type": "text",
					"enabled": true
				}
			],
			"dataMode": "params",
			"tests": "",
			"currentHelper": "normal",
			"helperAttributes": {},
			"time": 1498125536926,
			"name": "关注列表",
			"description": "",
			"collectionId": "7a113a39-138a-3eda-00e1-3e6fd4eed82f"
		},
		{
			"id": "5be820de-65c8-33c6-e2a2-1797d89b4492",
			"headers": "",
			"headerData": [],
			"url": "http://jiancai.cq1b1.com/api.php/User/kaidian_list",
			"queryParams": [],
			"preRequestScript": "",
			"pathVariables": {},
			"pathVariableData": [],
			"method": "POST",
			"data": [
				{
					"key": "version",
					"value": "1.1",
					"type": "text",
					"enabled": true
				},
				{
					"key": "apikey",
					"value": "f74dd39951a0b6bbed0fe73606ea5476",
					"type": "text",
					"enabled": true
				},
				{
					"key": "user_id",
					"value": "1",
					"type": "text",
					"enabled": true
				}
			],
			"dataMode": "params",
			"tests": "",
			"currentHelper": "normal",
			"helperAttributes": {},
			"time": 1497939861491,
			"name": "申请开店列表",
			"description": "",
			"collectionId": "7a113a39-138a-3eda-00e1-3e6fd4eed82f"
		},
		{
			"id": "703793b0-2f0c-9516-3c14-1be6b37c4872",
			"headers": "",
			"headerData": [],
			"url": "http://jiancai.cq1b1.com/api.php/Login",
			"queryParams": [],
			"preRequestScript": "",
			"pathVariables": {},
			"pathVariableData": [],
			"method": "POST",
			"data": [
				{
					"key": "version",
					"value": "1.1",
					"type": "text",
					"enabled": true
				},
				{
					"key": "apikey",
					"value": "f74dd39951a0b6bbed0fe73606ea5476",
					"type": "text",
					"enabled": true
				},
				{
					"key": "phone",
					"value": "15696154320",
					"type": "text",
					"enabled": true
				},
				{
					"key": "pass",
					"value": "123456",
					"type": "text",
					"enabled": true
				}
			],
			"dataMode": "params",
			"tests": "",
			"currentHelper": "normal",
			"helperAttributes": {},
			"time": 1497924684891,
			"name": "登陆",
			"description": "",
			"collectionId": "7a113a39-138a-3eda-00e1-3e6fd4eed82f"
		},
		{
			"id": "72aebc71-c50c-951d-06db-209404e00736",
			"headers": "",
			"headerData": [],
			"url": "http://jiancai.cq1b1.com/api.php/Public/bus_details",
			"queryParams": [],
			"preRequestScript": "",
			"pathVariables": {},
			"pathVariableData": [],
			"method": "POST",
			"data": [
				{
					"key": "version",
					"value": "1.1",
					"type": "text",
					"enabled": true
				},
				{
					"key": "apikey",
					"value": "f74dd39951a0b6bbed0fe73606ea5476",
					"type": "text",
					"enabled": true
				},
				{
					"key": "bus_id",
					"value": "1",
					"type": "text",
					"enabled": true
				},
				{
					"key": "user_id",
					"value": "1",
					"description": "",
					"type": "text",
					"enabled": true
				},
				{
					"key": "page",
					"value": "1",
					"description": "",
					"type": "text",
					"enabled": true
				},
				{
					"key": "type_id",
					"value": "2",
					"description": "",
					"type": "text",
					"enabled": true
				},
				{
					"key": "price",
					"value": "price_s",
					"description": "",
					"type": "text",
					"enabled": true
				},
				{
					"key": "sales",
					"value": "sales_s",
					"description": "",
					"type": "text",
					"enabled": true
				}
			],
			"dataMode": "params",
			"tests": "",
			"currentHelper": "normal",
			"helperAttributes": {},
			"time": 1498182255558,
			"name": "店铺首页",
			"description": "page：翻页；\ntype_id：分类id；\nprice：价格排序，price_s：价格升序，price_j：价格降序；\nsales：销量排序，sales_s：销量升序，sales_j：销量降序；",
			"collectionId": "7a113a39-138a-3eda-00e1-3e6fd4eed82f"
		},
		{
			"id": "73bc69f5-b918-444d-9d98-e9f0a38c5106",
			"headers": "",
			"headerData": [],
			"url": "http://jiancai.cq1b1.com/api.php/User/faceedit",
			"queryParams": [],
			"preRequestScript": "",
			"pathVariables": {},
			"pathVariableData": [],
			"method": "POST",
			"data": [
				{
					"key": "version",
					"value": "1.1",
					"type": "text",
					"enabled": true
				},
				{
					"key": "apikey",
					"value": "f74dd39951a0b6bbed0fe73606ea5476",
					"type": "text",
					"enabled": true
				},
				{
					"key": "user_id",
					"value": "1",
					"type": "text",
					"enabled": true
				},
				{
					"key": "face",
					"value": "",
					"description": "",
					"type": "file",
					"enabled": true
				}
			],
			"dataMode": "params",
			"tests": "",
			"currentHelper": "normal",
			"helperAttributes": {},
			"time": 1497926404327,
			"name": "修改头像",
			"description": "",
			"collectionId": "7a113a39-138a-3eda-00e1-3e6fd4eed82f"
		},
		{
			"id": "830f36a8-db8c-0f0b-610f-6fcdf33377ec",
			"headers": "",
			"headerData": [],
			"url": "http://jiancai.cq1b1.com/api.php/User/unameedit",
			"queryParams": [],
			"preRequestScript": "",
			"pathVariables": {},
			"pathVariableData": [],
			"method": "POST",
			"data": [
				{
					"key": "version",
					"value": "1.1",
					"type": "text",
					"enabled": true
				},
				{
					"key": "apikey",
					"value": "f74dd39951a0b6bbed0fe73606ea5476",
					"type": "text",
					"enabled": true
				},
				{
					"key": "user_id",
					"value": "1",
					"type": "text",
					"enabled": true
				},
				{
					"key": "user_name",
					"value": "老大",
					"description": "",
					"type": "text",
					"enabled": true
				}
			],
			"dataMode": "params",
			"tests": "",
			"currentHelper": "normal",
			"helperAttributes": {},
			"time": 1497926343845,
			"name": "修改昵称",
			"description": "",
			"collectionId": "7a113a39-138a-3eda-00e1-3e6fd4eed82f"
		},
		{
			"id": "939d3449-fd9d-8d96-cd0c-6129a5592e06",
			"headers": "",
			"headerData": [],
			"url": "http://jiancai.cq1b1.com/api.php/Public/goods_details",
			"queryParams": [],
			"preRequestScript": "",
			"pathVariables": {},
			"pathVariableData": [],
			"method": "POST",
			"data": [
				{
					"key": "version",
					"value": "1.1",
					"type": "text",
					"enabled": true
				},
				{
					"key": "apikey",
					"value": "f74dd39951a0b6bbed0fe73606ea5476",
					"type": "text",
					"enabled": true
				},
				{
					"key": "goods_id",
					"value": "1",
					"type": "text",
					"enabled": true
				},
				{
					"key": "user_id",
					"value": "1",
					"type": "text",
					"enabled": true
				}
			],
			"dataMode": "params",
			"tests": "",
			"currentHelper": "normal",
			"helperAttributes": {},
			"time": 1498182992288,
			"name": "商品详情",
			"description": "",
			"collectionId": "7a113a39-138a-3eda-00e1-3e6fd4eed82f"
		},
		{
			"id": "b9b18491-5b3e-c5b8-51b3-3fa6892eb8eb",
			"headers": "",
			"headerData": [],
			"url": "http://jiancai.cq1b1.com/api.php/Public/shoucang_list",
			"queryParams": [],
			"preRequestScript": "",
			"pathVariables": {},
			"pathVariableData": [],
			"method": "POST",
			"data": [
				{
					"key": "version",
					"value": "1.1",
					"type": "text",
					"enabled": true
				},
				{
					"key": "apikey",
					"value": "f74dd39951a0b6bbed0fe73606ea5476",
					"type": "text",
					"enabled": true
				},
				{
					"key": "user_id",
					"value": "1",
					"type": "text",
					"enabled": true
				}
			],
			"dataMode": "params",
			"tests": "",
			"currentHelper": "normal",
			"helperAttributes": {},
			"time": 1498178725877,
			"name": "收藏列表",
			"description": "",
			"collectionId": "7a113a39-138a-3eda-00e1-3e6fd4eed82f"
		},
		{
			"id": "bb9aba83-d84d-aeb6-fc5c-b71e30e8f423",
			"headers": "",
			"headerData": [],
			"url": "http://jiancai.cq1b1.com/api.php/Register/register_yzm",
			"queryParams": [],
			"preRequestScript": "",
			"pathVariables": {},
			"pathVariableData": [],
			"method": "POST",
			"data": [
				{
					"key": "version",
					"value": "1.1",
					"type": "text",
					"enabled": true
				},
				{
					"key": "apikey",
					"value": "f74dd39951a0b6bbed0fe73606ea5476",
					"type": "text",
					"enabled": true
				},
				{
					"key": "phone",
					"value": "15696154320",
					"type": "text",
					"enabled": true
				}
			],
			"dataMode": "params",
			"tests": "",
			"currentHelper": "normal",
			"helperAttributes": {},
			"time": 1497924203091,
			"name": "获取注册验证",
			"description": "",
			"collectionId": "7a113a39-138a-3eda-00e1-3e6fd4eed82f"
		},
		{
			"id": "beb2e471-954e-9e41-5040-d714fd031150",
			"headers": "",
			"headerData": [],
			"url": "http://jiancai.cq1b1.com/api.php/Public",
			"queryParams": [],
			"preRequestScript": "",
			"pathVariables": {},
			"pathVariableData": [],
			"method": "POST",
			"data": [
				{
					"key": "version",
					"value": "1.1",
					"type": "text",
					"enabled": true
				},
				{
					"key": "apikey",
					"value": "f74dd39951a0b6bbed0fe73606ea5476",
					"type": "text",
					"enabled": true
				},
				{
					"key": "ac",
					"value": "zuixin",
					"type": "text",
					"enabled": true
				},
				{
					"key": "page",
					"value": "1",
					"type": "text",
					"enabled": true
				}
			],
			"dataMode": "params",
			"tests": "",
			"currentHelper": "normal",
			"helperAttributes": {},
			"time": 1497940001454,
			"name": "首页",
			"description": "ac：zuixin：最新,remen：热门;\npage：分页页码；",
			"collectionId": "7a113a39-138a-3eda-00e1-3e6fd4eed82f"
		},
		{
			"id": "bf7fc7ec-162d-e6fe-50c9-fb4781e33b39",
			"headers": "",
			"headerData": [],
			"url": "http://jiancai.cq1b1.com/api.php/User",
			"queryParams": [],
			"preRequestScript": "",
			"pathVariables": {},
			"pathVariableData": [],
			"method": "POST",
			"data": [
				{
					"key": "version",
					"value": "1.1",
					"type": "text",
					"enabled": true
				},
				{
					"key": "apikey",
					"value": "f74dd39951a0b6bbed0fe73606ea5476",
					"type": "text",
					"enabled": true
				},
				{
					"key": "user_id",
					"value": "1",
					"type": "text",
					"enabled": true
				}
			],
			"dataMode": "params",
			"tests": "",
			"currentHelper": "normal",
			"helperAttributes": {},
			"time": 1497926190871,
			"name": "会员中心",
			"description": "",
			"collectionId": "7a113a39-138a-3eda-00e1-3e6fd4eed82f"
		},
		{
			"id": "d1615470-1d86-4ed9-1ee8-ca8b7dd89ed0",
			"headers": "",
			"headerData": [],
			"url": "http://jiancai.cq1b1.com/api.php/Public/guanzhu_del",
			"queryParams": [],
			"preRequestScript": "",
			"pathVariables": {},
			"pathVariableData": [],
			"method": "POST",
			"data": [
				{
					"key": "version",
					"value": "1.1",
					"type": "text",
					"enabled": true
				},
				{
					"key": "apikey",
					"value": "f74dd39951a0b6bbed0fe73606ea5476",
					"type": "text",
					"enabled": true
				},
				{
					"key": "user_id",
					"value": "1",
					"type": "text",
					"enabled": true
				},
				{
					"key": "bus_id",
					"value": "1",
					"description": "",
					"type": "text",
					"enabled": true
				}
			],
			"dataMode": "params",
			"tests": "",
			"currentHelper": "normal",
			"helperAttributes": {},
			"time": 1498125470794,
			"name": "删除关注",
			"description": "",
			"collectionId": "7a113a39-138a-3eda-00e1-3e6fd4eed82f"
		},
		{
			"id": "dfc53445-7ca8-2640-cef8-07417a1d6299",
			"headers": "",
			"headerData": [],
			"url": "http://jiancai.cq1b1.com/api.php/Public/type_list",
			"queryParams": [],
			"preRequestScript": "",
			"pathVariables": {},
			"pathVariableData": [],
			"method": "POST",
			"data": [
				{
					"key": "version",
					"value": "1.1",
					"type": "text",
					"enabled": true
				},
				{
					"key": "apikey",
					"value": "f74dd39951a0b6bbed0fe73606ea5476",
					"type": "text",
					"enabled": true
				},
				{
					"key": "type_id",
					"value": "",
					"type": "text",
					"enabled": true
				}
			],
			"dataMode": "params",
			"tests": "",
			"currentHelper": "normal",
			"helperAttributes": {},
			"time": 1497940063627,
			"name": "获取分类",
			"description": "type_id：分类id，传入分类id得到该分类下子分类",
			"collectionId": "7a113a39-138a-3eda-00e1-3e6fd4eed82f"
		},
		{
			"id": "f764ab22-bdb0-38a2-891c-d06a945cc822",
			"headers": "",
			"headerData": [],
			"url": "http://jiancai.cq1b1.com/api.php/Public/shoucang_add",
			"queryParams": [],
			"preRequestScript": "",
			"pathVariables": {},
			"pathVariableData": [],
			"method": "POST",
			"data": [
				{
					"key": "version",
					"value": "1.1",
					"type": "text",
					"enabled": true
				},
				{
					"key": "apikey",
					"value": "f74dd39951a0b6bbed0fe73606ea5476",
					"type": "text",
					"enabled": true
				},
				{
					"key": "user_id",
					"value": "1",
					"type": "text",
					"enabled": true
				},
				{
					"key": "goods_id",
					"value": "1",
					"type": "text",
					"enabled": true
				}
			],
			"dataMode": "params",
			"tests": "",
			"currentHelper": "normal",
			"helperAttributes": {},
			"time": 1498178732848,
			"name": "添加收藏",
			"description": "user_id：用户id；\nalbum_id：相册id",
			"collectionId": "7a113a39-138a-3eda-00e1-3e6fd4eed82f"
		}
	]
}